echoof/__init__.py
echoof/base.py
echoof/cli.py
echoof/logger.py
echoof-0.1.1.dist-info/LICENSE
echoof-0.1.1.dist-info/METADATA
echoof-0.1.1.dist-info/WHEEL
echoof-0.1.1.dist-info/entry_points.txt
echoof-0.1.1.dist-info/top_level.txt
echoof-0.1.1.dist-info/RECORD
